README.md
requirements.txt
setup.py
fastweb/__init__.py
fastweb/accesspoint.py
fastweb/cache.py
fastweb/compat.py
fastweb/components.py
fastweb/exception.py
fastweb/loader.py
fastweb/manager.py
fastweb/pool.py
fastweb/script.py
fastweb/service.py
fastweb/task.py
fastweb/web.py
fastweb.egg-info/PKG-INFO
fastweb.egg-info/SOURCES.txt
fastweb.egg-info/dependency_links.txt
fastweb.egg-info/entry_points.txt
fastweb.egg-info/requires.txt
fastweb.egg-info/top_level.txt
fastweb/command/__init__.py
fastweb/command/fast.py
fastweb/command/service/__init__.py
fastweb/command/service/thrift.py
fastweb/component/__init__.py
fastweb/component/request.py
fastweb/component/task.py
fastweb/component/db/__init__.py
fastweb/component/db/mongo.py
fastweb/component/db/mysql.py
fastweb/component/db/rds.py
fastweb/component/rpc/__init__.py
fastweb/component/rpc/tft.py
fastweb/setting/__init__.py
fastweb/setting/default_component.py
fastweb/setting/default_connection_component.py
fastweb/setting/default_errcode.py
fastweb/setting/default_logging.py
fastweb/spec/__init__.py
fastweb/spec/req.py
fastweb/spec/torcelery.py
fastweb/spec/idl/__init__.py
fastweb/spec/idl/ast.py
fastweb/spec/idl/lexer.py
fastweb/spec/idl/parser.py
fastweb/test/__init__.py
fastweb/test/client.py
fastweb/test/configuration.py
fastweb/test/interactive.py
fastweb/test/mongo.py
fastweb/test/process.py
fastweb/test/service_server.py
fastweb/test/system.py
fastweb/test/task.py
fastweb/test/test_loader.py
fastweb/test/test_manager.py
fastweb/test/test_mongo.py
fastweb/test/test_mysql.py
fastweb/test/test_pool.py
fastweb/test/test_redis.py
fastweb/test/test_thrift.py
fastweb/test/tool.py
fastweb/test/tormysql.py
fastweb/test/web.py
fastweb/test/worker.py
fastweb/test/fastweb_thrift_async/__init__.py
fastweb/test/fastweb_thrift_async/HelloService/HelloService.py
fastweb/test/fastweb_thrift_async/HelloService/__init__.py
fastweb/test/fastweb_thrift_async/HelloService/constants.py
fastweb/test/fastweb_thrift_async/HelloService/ttypes.py
fastweb/test/fastweb_thrift_sync/__init__.py
fastweb/test/fastweb_thrift_sync/HelloService/HelloService.py
fastweb/test/fastweb_thrift_sync/HelloService/__init__.py
