Metadata-Version: 2.1
Name: fastweb
Version: 1.6.0.20
Summary: fastweb is a web-server integration solution. It based on tornado, celery, thrift.
Home-page: https://github.com/BSlience/fastweb
Author: bslience
Author-email: zhangchunyang_pri@126.com
License: UNKNOWN
Platform: UNKNOWN
